find_anything/__init__.py
find_anything/models.py
find_anything/object_matcher.py
find_anything/utils.py
find_anything/embedding_repository/__init__.py
find_anything/embedding_repository/base.py
find_anything/embedding_repository/protocol.py
find_anything/feature_encoder/__init__.py
find_anything/feature_encoder/dinov2.py
find_anything/feature_encoder/protocol.py
find_anything/mask/__init__.py
find_anything/mask/generator/__init__.py
find_anything/mask/generator/fastsam.py
find_anything/mask/generator/protocol.py
find_anything/mask/pooler/__init__.py
find_anything/mask/pooler/dense_feature.py
find_anything/mask/pooler/protocol.py
find_anything/mask/selector/__init__.py
find_anything/mask/selector/protocol.py
find_anything/mask/selector/topk.py
find_anything-1.3.0.dist-info/licenses/LICENSE
find_anything-1.3.0.dist-info/METADATA
find_anything-1.3.0.dist-info/WHEEL
find_anything-1.3.0.dist-info/top_level.txt
find_anything-1.3.0.dist-info/RECORD
